gouda/__init__.py
gouda/binaryconfusionmatrix.py
gouda/color_lists.py
gouda/colors.py
gouda/confusionmatrix.py
gouda/constants.py
gouda/data_methods.py
gouda/display.py
gouda/file_methods.py
gouda/general.py
gouda/goudapath.py
gouda/image.py
gouda/moving_stats.py
gouda/plotting.py
gouda/symbols.py
gouda/typing.py
gouda/video.py
gouda-0.6.6.dist-info/LICENSE.txt
gouda-0.6.6.dist-info/METADATA
gouda-0.6.6.dist-info/WHEEL
gouda-0.6.6.dist-info/top_level.txt
gouda-0.6.6.dist-info/RECORD
